pioneer/leddar_utils_cpp.cpython-36m-x86_64-linux-gnu.so
pioneer/leddar_utils_cpp.cpython-37m-x86_64-linux-gnu.so
pioneer/libleddar_utils_lcax.so
pioneer/common/gui/Actors.py
pioneer/common/gui/Array.py
pioneer/common/gui/Camera.py
pioneer/common/gui/Clouds.py
pioneer/common/gui/CustomActors.py
pioneer/common/gui/CustomAttribs.py
pioneer/common/gui/CustomEffects.py
pioneer/common/gui/Effect.py
pioneer/common/gui/Geometry.py
pioneer/common/gui/Image.py
pioneer/common/gui/InFboRenderer.py
pioneer/common/gui/LeddarUtils.py
pioneer/common/gui/MPLFigures.py
pioneer/common/gui/Product.py
pioneer/common/gui/Sensor.py
pioneer/common/gui/SensorFilters.py
pioneer/common/gui/Table.py
pioneer/common/gui/Traces.py
pioneer/common/gui/Transforms.py
pioneer/common/gui/Viewport.py
pioneer/common/gui/__init__.py
pioneer/common/gui/interactive.py
pioneer/common/gui/utils.py
pioneer/common/gui/qml/__init__.py
pioneer/common/gui/qml/root.qml
pioneer/common/gui/qml/root_CheddarConfig.qml
pioneer/common/gui/qml/root_LeddarVP.qml
pioneer/common/gui/qml/root_LeddarVPwithTraces.qml
pioneer/common/gui/qml/root_MPL.qml
pioneer/common/gui/qml/root_POCFrancois.qml
pioneer/common/gui/qml/root_PointCloud.qml
pioneer/common/gui/qml/root_Projection.qml
pioneer/common/gui/qml/root_TestPickingCamera.qml
pioneer/common/gui/qml/root_scene_builder_city_editor.qml
pioneer/common/gui/qml/root_scene_builder_dataset_editor.qml
pioneer/common/gui/qml/root_simulator.qml
pioneer/common/gui/qml/root_test_sim.qml
pioneer/common/gui/qml/Examples/CameraIntrinsincs.qml
pioneer/common/gui/qml/Examples/ExampleDataset.qml
pioneer/common/gui/qml/Examples/ExampleLabeledDataset.qml
pioneer/common/gui/qml/Examples/ExampleLive.qml
pioneer/common/gui/qml/Examples/ExampleReplay.qml
pioneer/common/gui/qml/Examples/qmldir
pioneer/common/gui/qml/Misc/Utils.js
pioneer/common/gui/qml/Misc/qmldir
pioneer/common/gui/qml/MultiSensorViewer/CalibPanel.qml
pioneer_common_gui-1.4.0.dist-info/DESCRIPTION.rst
pioneer_common_gui-1.4.0.dist-info/METADATA
pioneer_common_gui-1.4.0.dist-info/RECORD
pioneer_common_gui-1.4.0.dist-info/WHEEL
pioneer_common_gui-1.4.0.dist-info/dependency_links.txt
pioneer_common_gui-1.4.0.dist-info/metadata.json
pioneer_common_gui-1.4.0.dist-info/top_level.txt
