Metadata-Version: 2.0
Name: pioneer-common-gui
Version: 1.4.0
Summary: Pioneer gui utility package
Home-page: UNKNOWN
Author: Leddartech
Author-email: UNKNOWN
License: UNKNOWN
Platform: UNKNOWN
Requires-Dist: PyOpenGL
Requires-Dist: PyQt5 (==5.14)
Requires-Dist: PyQtChart (==5.14)
Requires-Dist: Shapely
Requires-Dist: future
Requires-Dist: matplotlib
Requires-Dist: numpy
Requires-Dist: opencv-python
Requires-Dist: pioneer-common
Requires-Dist: pycollada
Requires-Dist: tqdm
Requires-Dist: transforms3d
Requires-Dist: utm
